AUTHORS
LICENSE
MANIFEST.in
README.md
setup.py
wysiweb/__init__.py
wysiweb.egg-info/PKG-INFO
wysiweb.egg-info/SOURCES.txt
wysiweb.egg-info/dependency_links.txt
wysiweb.egg-info/not-zip-safe
wysiweb.egg-info/top_level.txt