Metadata-Version: 1.0
Name: wysiweb
Version: 0.1.0
Summary: File-system based router and static website generator
Home-page: http://jspi.es/wysiweb
Author: Jeffrey R. Spies
Author-email: jspies@gmail.com
License: LICENSE
Platform: any
Classifier: Development Status :: 4 - Beta
Classifier: Natural Language :: English
Classifier: Operating System :: OS Independent
Classifier: Intended Audience :: Developers
Classifier: Programming Language :: Python
Classifier: License :: OSI Approved :: Apache Software License
Classifier: Topic :: Software Development :: Libraries :: Python Modules
